MANIFEST.in
README.md
requirements.txt
setup.py
crossroads_schematization.egg-info/PKG-INFO
crossroads_schematization.egg-info/SOURCES.txt
crossroads_schematization.egg-info/dependency_links.txt
crossroads_schematization.egg-info/entry_points.txt
crossroads_schematization.egg-info/top_level.txt
crschem/__init__.py
crschem/cmd.py
crschem/crossroad_schematization.py
crschem/processing.py
crschem/utils.py
crschem/model/branch.py
crschem/model/crossing.py
crschem/model/simple_way.py
crschem/model/straight_sidewalk.py
crschem/model/straight_way.py
crschem/model/traffic_island.py
crschem/model/turning_sidewalk.py
crschem/model/__pycache__/branch.cpython-311.pyc
crschem/model/__pycache__/crossing.cpython-311.pyc
crschem/model/__pycache__/simple_way.cpython-311.pyc
crschem/model/__pycache__/straight_sidewalk.cpython-311.pyc
crschem/model/__pycache__/straight_way.cpython-311.pyc
crschem/model/__pycache__/traffic_island.cpython-311.pyc
crschem/model/__pycache__/turning_sidewalk.cpython-311.pyc
crschem/normalization/normalized_branch.py
crschem/normalization/normalizer.py
crschem/normalization/__pycache__/normalized_branch.cpython-311.pyc
crschem/normalization/__pycache__/normalizer.cpython-311.pyc
crschem/resources/400/crossing-3-300.svg
crschem/resources/400/crossing-3-96.svg
crschem/resources/400/island-300-white.svg
crschem/resources/400/island-300.svg
crschem/resources/400/island-96-white.svg
crschem/resources/400/island-96.svg
crschem/resources/400/point-300.svg
crschem/resources/400/point-96.svg
crschem/resources/400/style-300.xml
crschem/resources/400/style-96.xml
crschem/resources/500/crossing-3-300.svg
crschem/resources/500/crossing-3-96.svg
crschem/resources/500/island-300-white.svg
crschem/resources/500/island-300.svg
crschem/resources/500/island-96-white.svg
crschem/resources/500/island-96.svg
crschem/resources/500/point-300.svg
crschem/resources/500/point-96.svg
crschem/resources/500/style-300.xml
crschem/resources/500/style-96.xml