Metadata-Version: 2.1
Name: crossroads-schematization
Version: 0.3.1
Summary: Crossroads schematization is a python tool that produces automatic schematization of intersections from OpenStreetMap.
Home-page: https://github.com/jmtrivial/crossroads-schematization/
Author: Jean-Marie Favreau
Author-email: j-marie.favreau@uca.fr
License: AGPL-3.0
Classifier: License :: OSI Approved :: GNU Affero General Public License v3 or later (AGPLv3+)
Classifier: Programming Language :: Python :: 3
Classifier: Programming Language :: Python :: 3.7
